abx_plugin_pocket/__init__.py
abx_plugin_pocket/config.py
abx_plugin_pocket-2024.10.28.dist-info/METADATA
abx_plugin_pocket-2024.10.28.dist-info/WHEEL
abx_plugin_pocket-2024.10.28.dist-info/entry_points.txt
abx_plugin_pocket-2024.10.28.dist-info/RECORD
